pg_comtrade.py
pg_comtrade-0.0.2.dist-info/METADATA
pg_comtrade-0.0.2.dist-info/WHEEL
pg_comtrade-0.0.2.dist-info/licenses/LICENSE
pg_comtrade-0.0.2.dist-info/RECORD
