Metadata-Version: 2.3
Name: pg-comtrade
Version: 0.0.2
Summary: Python function to ingest data from UN Comtrade's bulk API to PostgreSQL
Project-URL: Source, https://github.com/uktrade/pg-comtrade
Author-email: Department for Business and Trade <sre@digital.trade.gov.uk>
License-File: LICENSE
Classifier: License :: OSI Approved :: MIT License
Classifier: Operating System :: OS Independent
Classifier: Programming Language :: Python :: 3
Requires-Python: >=3.8
Requires-Dist: pandas
Requires-Dist: sqlalchemy>=1.4.24
Provides-Extra: dev
Requires-Dist: psycopg2-binary; extra == 'dev'
Requires-Dist: pytest-cov; extra == 'dev'
Requires-Dist: pytest>=7.4.4; extra == 'dev'
